client_packages/__init__.py
client_packages/client/__init__.py
client_packages/client/add_contact.py
client_packages/client/client_database.py
client_packages/client/del_contact.py
client_packages/client/main_window.py
client_packages/client/main_window_conv.py
client_packages/client/start_client.py
client_packages/client/start_dialog.py
client_packages/client/transport.py
client_packages/common/__init__.py
client_packages/common/descriptors.py
client_packages/common/metaclasses.py
client_packages/common/utils.py
client_packages/common/variables.py
client_packages/doc/__init__.py
client_packages/doc/conf.py
client_packages/log/__init__.py
client_packages/log/config_log/__init__.py
client_packages/log/config_log/config_client_log.py
client_packages/log/config_log/decos.py
client_packages/unit_tests/__init__.py
client_packages/unit_tests/test_client.py
client_packages/unit_tests/test_utils.py
Client_messenger-0.2.dist-info/METADATA
Client_messenger-0.2.dist-info/WHEEL
Client_messenger-0.2.dist-info/top_level.txt
Client_messenger-0.2.dist-info/RECORD
